[{"model": "contenttypes.contenttype", "fields": {"app_label": "admin", "model": "logentry"}}, {"model": "contenttypes.contenttype", "fields": {"app_label": "auth", "model": "permission"}}, {"model": "contenttypes.contenttype", "fields": {"app_label": "auth", "model": "group"}}, {"model": "contenttypes.contenttype", "fields": {"app_label": "auth", "model": "user"}}, {"model": "contenttypes.contenttype", "fields": {"app_label": "contenttypes", "model": "contenttype"}}, {"model": "contenttypes.contenttype", "fields": {"app_label": "sessions", "model": "session"}}, {"model": "contenttypes.contenttype", "fields": {"app_label": "insta", "model": "userfollow"}}, {"model": "contenttypes.contenttype", "fields": {"app_label": "insta", "model": "instapost"}}, {"model": "contenttypes.contenttype", "fields": {"app_label": "authtoken", "model": "token"}}, {"model": "contenttypes.contenttype", "fields": {"app_label": "authtoken", "model": "tokenproxy"}}, {"model": "sessions.session", "pk": "jlrafwov4kz9uxv9mflzliashu24a5ob", "fields": {"session_data": ".eJxVjEEOwiAQRe_C2pCpgIBL956hmYEZqRpISrsy3l2bdKHb_977LzXiupRx7TyPU1ZnNajD70aYHlw3kO9Yb02nVpd5Ir0peqddX1vm52V3_w4K9vKtwTlvQhaKycHgCeXEImBFMB7BBIhBLBAzZwyQ0TtLxAYNokvCot4f-fE5Tg:1nJQKZ:s7ckavOhuax_lP2S4Jr1V3VadHmHsAGTdEtmR-mXz9A", "expire_date": "2022-02-28T01:39:07.563Z"}}, {"model": "sessions.session", "pk": "r06gj36vjso4vs4t1cq82h8xkwzn3uo2", "fields": {"session_data": ".eJxVjEEOwiAQRe_C2pCpgIBL956hmYEZqRpISrsy3l2bdKHb_977LzXiupRx7TyPU1ZnNajD70aYHlw3kO9Yb02nVpd5Ir0peqddX1vm52V3_w4K9vKtwTlvQhaKycHgCeXEImBFMB7BBIhBLBAzZwyQ0TtLxAYNokvCot4f-fE5Tg:1nJG7L:paoCUbKEfHQkxaV6hf-J0x4qk5xmX8ECp3YlvrmBzA4", "expire_date": "2022-02-27T14:44:47.395Z"}}, {"model": "auth.permission", "fields": {"name": "Can add log entry", "content_type": ["admin", "logentry"], "codename": "add_logentry"}}, {"model": "auth.permission", "fields": {"name": "Can change log entry", "content_type": ["admin", "logentry"], "codename": "change_logentry"}}, {"model": "auth.permission", "fields": {"name": "Can delete log entry", "content_type": ["admin", "logentry"], "codename": "delete_logentry"}}, {"model": "auth.permission", "fields": {"name": "Can view log entry", "content_type": ["admin", "logentry"], "codename": "view_logentry"}}, {"model": "auth.permission", "fields": {"name": "Can add permission", "content_type": ["auth", "permission"], "codename": "add_permission"}}, {"model": "auth.permission", "fields": {"name": "Can change permission", "content_type": ["auth", "permission"], "codename": "change_permission"}}, {"model": "auth.permission", "fields": {"name": "Can delete permission", "content_type": ["auth", "permission"], "codename": "delete_permission"}}, {"model": "auth.permission", "fields": {"name": "Can view permission", "content_type": ["auth", "permission"], "codename": "view_permission"}}, {"model": "auth.permission", "fields": {"name": "Can add group", "content_type": ["auth", "group"], "codename": "add_group"}}, {"model": "auth.permission", "fields": {"name": "Can change group", "content_type": ["auth", "group"], "codename": "change_group"}}, {"model": "auth.permission", "fields": {"name": "Can delete group", "content_type": ["auth", "group"], "codename": "delete_group"}}, {"model": "auth.permission", "fields": {"name": "Can view group", "content_type": ["auth", "group"], "codename": "view_group"}}, {"model": "auth.permission", "fields": {"name": "Can add user", "content_type": ["auth", "user"], "codename": "add_user"}}, {"model": "auth.permission", "fields": {"name": "Can change user", "content_type": ["auth", "user"], "codename": "change_user"}}, {"model": "auth.permission", "fields": {"name": "Can delete user", "content_type": ["auth", "user"], "codename": "delete_user"}}, {"model": "auth.permission", "fields": {"name": "Can view user", "content_type": ["auth", "user"], "codename": "view_user"}}, {"model": "auth.permission", "fields": {"name": "Can add content type", "content_type": ["contenttypes", "contenttype"], "codename": "add_contenttype"}}, {"model": "auth.permission", "fields": {"name": "Can change content type", "content_type": ["contenttypes", "contenttype"], "codename": "change_contenttype"}}, {"model": "auth.permission", "fields": {"name": "Can delete content type", "content_type": ["contenttypes", "contenttype"], "codename": "delete_contenttype"}}, {"model": "auth.permission", "fields": {"name": "Can view content type", "content_type": ["contenttypes", "contenttype"], "codename": "view_contenttype"}}, {"model": "auth.permission", "fields": {"name": "Can add session", "content_type": ["sessions", "session"], "codename": "add_session"}}, {"model": "auth.permission", "fields": {"name": "Can change session", "content_type": ["sessions", "session"], "codename": "change_session"}}, {"model": "auth.permission", "fields": {"name": "Can delete session", "content_type": ["sessions", "session"], "codename": "delete_session"}}, {"model": "auth.permission", "fields": {"name": "Can view session", "content_type": ["sessions", "session"], "codename": "view_session"}}, {"model": "auth.permission", "fields": {"name": "Can add UserFollow", "content_type": ["insta", "userfollow"], "codename": "add_userfollow"}}, {"model": "auth.permission", "fields": {"name": "Can change UserFollow", "content_type": ["insta", "userfollow"], "codename": "change_userfollow"}}, {"model": "auth.permission", "fields": {"name": "Can delete UserFollow", "content_type": ["insta", "userfollow"], "codename": "delete_userfollow"}}, {"model": "auth.permission", "fields": {"name": "Can view UserFollow", "content_type": ["insta", "userfollow"], "codename": "view_userfollow"}}, {"model": "auth.permission", "fields": {"name": "Can add InstaPost", "content_type": ["insta", "instapost"], "codename": "add_instapost"}}, {"model": "auth.permission", "fields": {"name": "Can change InstaPost", "content_type": ["insta", "instapost"], "codename": "change_instapost"}}, {"model": "auth.permission", "fields": {"name": "Can delete InstaPost", "content_type": ["insta", "instapost"], "codename": "delete_instapost"}}, {"model": "auth.permission", "fields": {"name": "Can view InstaPost", "content_type": ["insta", "instapost"], "codename": "view_instapost"}}, {"model": "auth.permission", "fields": {"name": "Can add Token", "content_type": ["authtoken", "token"], "codename": "add_token"}}, {"model": "auth.permission", "fields": {"name": "Can change Token", "content_type": ["authtoken", "token"], "codename": "change_token"}}, {"model": "auth.permission", "fields": {"name": "Can delete Token", "content_type": ["authtoken", "token"], "codename": "delete_token"}}, {"model": "auth.permission", "fields": {"name": "Can view Token", "content_type": ["authtoken", "token"], "codename": "view_token"}}, {"model": "auth.permission", "fields": {"name": "Can add token", "content_type": ["authtoken", "tokenproxy"], "codename": "add_tokenproxy"}}, {"model": "auth.permission", "fields": {"name": "Can change token", "content_type": ["authtoken", "tokenproxy"], "codename": "change_tokenproxy"}}, {"model": "auth.permission", "fields": {"name": "Can delete token", "content_type": ["authtoken", "tokenproxy"], "codename": "delete_tokenproxy"}}, {"model": "auth.permission", "fields": {"name": "Can view token", "content_type": ["authtoken", "tokenproxy"], "codename": "view_tokenproxy"}}, {"model": "auth.user", "fields": {"password": "pbkdf2_sha256$320000$gNjVS9DN2lcYx26MXHzCU6$/uIgIR9WTv7k+015Ch1REw/+fpuSLFCmRzCG/FIOrJc=", "last_login": "2022-02-14T01:39:07.560Z", "is_superuser": true, "username": "jay", "first_name": "", "last_name": "", "email": "", "is_staff": true, "is_active": true, "date_joined": "2022-02-13T14:44:24.382Z", "groups": [], "user_permissions": []}}, {"model": "auth.user", "fields": {"password": "pbkdf2_sha256$320000$WZO2hUlByXasldNE9yFqCe$XeTwTRxIDAaULMMgQ2o/Q7098c19Vh3+Puw/6Q45eTw=", "last_login": null, "is_superuser": false, "username": "user2", "first_name": "", "last_name": "", "email": "", "is_staff": false, "is_active": true, "date_joined": "2022-02-13T14:47:57Z", "groups": [], "user_permissions": []}}, {"model": "auth.user", "fields": {"password": "pbkdf2_sha256$320000$JBw9hUcOv2FjfbPt3OvvX1$+XNgqsuzWuDWMXh3gqrBDMSCKe6qyKerkPtHbbUKDMk=", "last_login": null, "is_superuser": false, "username": "user3", "first_name": "", "last_name": "", "email": "", "is_staff": false, "is_active": true, "date_joined": "2022-02-13T14:53:51Z", "groups": [], "user_permissions": []}}, {"model": "auth.user", "fields": {"password": "pbkdf2_sha256$320000$P5gPT242fQuK972Hv1wvIc$pjTaZlE8613qrNLrzz3aKl4ILpuYw+8yZ3iT/CD2a9Y=", "last_login": null, "is_superuser": false, "username": "user4", "first_name": "", "last_name": "", "email": "", "is_staff": false, "is_active": true, "date_joined": "2022-02-13T14:55:09Z", "groups": [], "user_permissions": []}}, {"model": "authtoken.token", "pk": "c7bb4ddca0a03a9dd66001b39197528031712714", "fields": {"user": ["jay"], "created": "2022-02-14T03:08:21.186Z"}}, {"model": "authtoken.token", "pk": "d79a19591b434ecac1d951086681b26e44e35b62", "fields": {"user": ["user3"], "created": "2022-02-14T03:08:21.192Z"}}, {"model": "authtoken.token", "pk": "df4e7fc26a93b8de61d14633d0bd2398a47547c7", "fields": {"user": ["user4"], "created": "2022-02-14T03:08:21.194Z"}}, {"model": "authtoken.token", "pk": "e3b8fd4dd04ca0c7c4e4ed8bfa7a160fbc2a45c7", "fields": {"user": ["user2"], "created": "2022-02-14T03:08:21.190Z"}}, {"model": "insta.instapost", "pk": 1, "fields": {"owner": ["user2"], "image_url": "https://mockinsta.com/post1", "caption": "https://mockinsta.com/post1", "post_added": "2022-02-13T16:00:59.025Z", "likes": []}}, {"model": "insta.instapost", "pk": 2, "fields": {"owner": ["user3"], "image_url": "https://mockinsta.com/post2", "caption": "https://mockinsta.com/post2", "post_added": "2022-02-13T16:00:59.025Z", "likes": [["jay"], ["user2"], ["user3"], ["user4"]]}}, {"model": "insta.instapost", "pk": 3, "fields": {"owner": ["user4"], "image_url": "https://mockinsta.com/post3", "caption": "https://mockinsta.com/post3", "post_added": "2022-02-13T16:00:59.025Z", "likes": [["user2"], ["user3"], ["user4"]]}}, {"model": "insta.userfollow", "pk": 1, "fields": {"user": ["user2"], "follower": ["user3"]}}, {"model": "insta.userfollow", "pk": 2, "fields": {"user": ["user2"], "follower": ["user4"]}}, {"model": "insta.userfollow", "pk": 3, "fields": {"user": ["user3"], "follower": ["user4"]}}, {"model": "admin.logentry", "pk": 1, "fields": {"action_time": "2022-02-13T14:47:57.548Z", "user": ["jay"], "content_type": ["auth", "user"], "object_id": "2", "object_repr": "user1", "action_flag": 1, "change_message": "[{\"added\": {}}]"}}, {"model": "admin.logentry", "pk": 2, "fields": {"action_time": "2022-02-13T14:53:36.500Z", "user": ["jay"], "content_type": ["insta", "instapost"], "object_id": "1", "object_repr": "jay: https://mockinsta.com/post1", "action_flag": 1, "change_message": "[{\"added\": {}}]"}}, {"model": "admin.logentry", "pk": 3, "fields": {"action_time": "2022-02-13T14:53:52.197Z", "user": ["jay"], "content_type": ["auth", "user"], "object_id": "3", "object_repr": "user2", "action_flag": 1, "change_message": "[{\"added\": {}}]"}}, {"model": "admin.logentry", "pk": 4, "fields": {"action_time": "2022-02-13T14:54:14.986Z", "user": ["jay"], "content_type": ["insta", "instapost"], "object_id": "2", "object_repr": "user1: https://mockinsta.com/post2", "action_flag": 1, "change_message": "[{\"added\": {}}]"}}, {"model": "admin.logentry", "pk": 5, "fields": {"action_time": "2022-02-13T14:54:30.431Z", "user": ["jay"], "content_type": ["insta", "instapost"], "object_id": "3", "object_repr": "user2: https://mockinsta.com/post3", "action_flag": 1, "change_message": "[{\"added\": {}}]"}}, {"model": "admin.logentry", "pk": 6, "fields": {"action_time": "2022-02-13T14:54:51.420Z", "user": ["jay"], "content_type": ["insta", "instapost"], "object_id": "2", "object_repr": "user2: https://mockinsta.com/post2", "action_flag": 2, "change_message": "[{\"changed\": {\"fields\": [\"Owner\"]}}]"}}, {"model": "admin.logentry", "pk": 7, "fields": {"action_time": "2022-02-13T14:55:09.638Z", "user": ["jay"], "content_type": ["auth", "user"], "object_id": "4", "object_repr": "user3", "action_flag": 1, "change_message": "[{\"added\": {}}]"}}, {"model": "admin.logentry", "pk": 8, "fields": {"action_time": "2022-02-13T14:55:15.750Z", "user": ["jay"], "content_type": ["insta", "instapost"], "object_id": "3", "object_repr": "user3: https://mockinsta.com/post3", "action_flag": 2, "change_message": "[{\"changed\": {\"fields\": [\"Owner\", \"Likes\"]}}]"}}, {"model": "admin.logentry", "pk": 9, "fields": {"action_time": "2022-02-13T14:55:25.378Z", "user": ["jay"], "content_type": ["insta", "instapost"], "object_id": "1", "object_repr": "user1: https://mockinsta.com/post1", "action_flag": 2, "change_message": "[{\"changed\": {\"fields\": [\"Owner\", \"Likes\"]}}]"}}, {"model": "admin.logentry", "pk": 10, "fields": {"action_time": "2022-02-13T15:53:42.283Z", "user": ["jay"], "content_type": ["insta", "userfollow"], "object_id": "1", "object_repr": "user2 follows user1", "action_flag": 1, "change_message": "[{\"added\": {}}]"}}, {"model": "admin.logentry", "pk": 11, "fields": {"action_time": "2022-02-13T15:54:02.625Z", "user": ["jay"], "content_type": ["insta", "userfollow"], "object_id": "2", "object_repr": "user3 follows user1", "action_flag": 1, "change_message": "[{\"added\": {}}]"}}, {"model": "admin.logentry", "pk": 12, "fields": {"action_time": "2022-02-14T02:11:32.413Z", "user": ["jay"], "content_type": ["insta", "instapost"], "object_id": "3", "object_repr": "user3: https://mockinsta.com/post3", "action_flag": 2, "change_message": "[{\"changed\": {\"fields\": [\"Likes\"]}}]"}}, {"model": "admin.logentry", "pk": 13, "fields": {"action_time": "2022-02-14T02:16:03.235Z", "user": ["jay"], "content_type": ["insta", "instapost"], "object_id": "1", "object_repr": "user1: https://mockinsta.com/post1", "action_flag": 2, "change_message": "[{\"changed\": {\"fields\": [\"Likes\"]}}]"}}, {"model": "admin.logentry", "pk": 14, "fields": {"action_time": "2022-02-14T02:16:14.483Z", "user": ["jay"], "content_type": ["insta", "instapost"], "object_id": "2", "object_repr": "user2: https://mockinsta.com/post2", "action_flag": 2, "change_message": "[{\"changed\": {\"fields\": [\"Likes\"]}}]"}}, {"model": "admin.logentry", "pk": 15, "fields": {"action_time": "2022-02-14T02:16:20.111Z", "user": ["jay"], "content_type": ["insta", "instapost"], "object_id": "3", "object_repr": "user3: https://mockinsta.com/post3", "action_flag": 2, "change_message": "[]"}}, {"model": "admin.logentry", "pk": 16, "fields": {"action_time": "2022-02-14T02:18:56.463Z", "user": ["jay"], "content_type": ["insta", "instapost"], "object_id": "2", "object_repr": "user2: https://mockinsta.com/post2", "action_flag": 2, "change_message": "[{\"changed\": {\"fields\": [\"Likes\"]}}]"}}, {"model": "admin.logentry", "pk": 17, "fields": {"action_time": "2022-02-14T05:53:53.450Z", "user": ["jay"], "content_type": ["auth", "user"], "object_id": "4", "object_repr": "user4", "action_flag": 2, "change_message": "[{\"changed\": {\"fields\": [\"Username\"]}}]"}}, {"model": "admin.logentry", "pk": 18, "fields": {"action_time": "2022-02-14T05:53:57.665Z", "user": ["jay"], "content_type": ["auth", "user"], "object_id": "3", "object_repr": "user3", "action_flag": 2, "change_message": "[{\"changed\": {\"fields\": [\"Username\"]}}]"}}, {"model": "admin.logentry", "pk": 19, "fields": {"action_time": "2022-02-14T05:54:02.400Z", "user": ["jay"], "content_type": ["auth", "user"], "object_id": "2", "object_repr": "user2", "action_flag": 2, "change_message": "[{\"changed\": {\"fields\": [\"Username\"]}}]"}}, {"model": "admin.logentry", "pk": 20, "fields": {"action_time": "2022-02-14T06:16:58.067Z", "user": ["jay"], "content_type": ["insta", "userfollow"], "object_id": "3", "object_repr": "user4 follows user3", "action_flag": 1, "change_message": "[{\"added\": {}}]"}}]